SurVigilance/__init__.py
SurVigilance/ui/__init__.py
SurVigilance/ui/_app.py
SurVigilance/ui/_settings.py
SurVigilance/ui/assets/survigilance_sticker.ico
SurVigilance/ui/pages/__init__.py
SurVigilance/ui/pages/search_page_daen.py
SurVigilance/ui/pages/search_page_dma.py
SurVigilance/ui/pages/search_page_faers.py
SurVigilance/ui/pages/search_page_lareb.py
SurVigilance/ui/pages/search_page_nzsmars.py
SurVigilance/ui/pages/search_page_vaers.py
SurVigilance/ui/pages/search_page_vigiaccess.py
SurVigilance/ui/scrapers/__init__.py
SurVigilance/ui/scrapers/check_internet_connectivity.py
SurVigilance/ui/scrapers/faers_links.py
SurVigilance/ui/scrapers/scrape_daen.py
SurVigilance/ui/scrapers/scrape_dma.py
SurVigilance/ui/scrapers/scrape_faers.py
SurVigilance/ui/scrapers/scrape_lareb.py
SurVigilance/ui/scrapers/scrape_nzsmars.py
SurVigilance/ui/scrapers/scrape_vaers.py
SurVigilance/ui/scrapers/scrape_vigiaccess.py
survigilance-1.0.1.dist-info/licenses/LICENSE
survigilance-1.0.1.dist-info/METADATA
survigilance-1.0.1.dist-info/WHEEL
survigilance-1.0.1.dist-info/top_level.txt
survigilance-1.0.1.dist-info/RECORD
