Metadata-Version: 2.4
Name: SurVigilance
Version: 1.0.1
Summary: SurVigilance: An application to collect pharmacovigilance data from safety databases around the world.
Classifier: Programming Language :: Python :: 3
Classifier: Programming Language :: Python :: 3 :: Only
Classifier: Programming Language :: Python :: 3.10
Classifier: Programming Language :: Python :: 3.11
Classifier: Programming Language :: Python :: 3.12
Classifier: Programming Language :: Python :: 3.13
Classifier: Environment :: Web Environment
Classifier: Intended Audience :: Science/Research
Requires-Python: >=3.10
License-File: LICENSE
Requires-Dist: streamlit>=1.49.1
Requires-Dist: seleniumbase<=4.44.15
Requires-Dist: pandas>=1.5.0
Requires-Dist: requests>=2.28.0
Requires-Dist: beautifulsoup4>=4.12.0
Requires-Dist: lxml>=6.0.0
Requires-Dist: openpyxl>=3.1.0
Dynamic: classifier
Dynamic: description
Dynamic: description-content-type
Dynamic: license-file
Dynamic: requires-dist
Dynamic: requires-python
Dynamic: summary
